[
  {
    "file": "src/main.c",
    "arguments": [
      "gcc",
      "-g",
      "-Wall",
      "-std=c11",
      "-fsanitize=address",
      "-c",
      "src/main.c",
      "-o",
      "obj/main.o",
      "-I",
      "headers",
      "-I",
      "dependencies/mathgl-8.0.3/include"
    ],
    "directory": "/home/yt/Documents/Bachelor Thesis/NN_with_time_signature_feature_map",
    "output": "obj/main.o"
  },
  {
    "file": "src/Matrix.c",
    "arguments": [
      "gcc",
      "-g",
      "-Wall",
      "-std=c11",
      "-fsanitize=address",
      "-c",
      "src/Matrix.c",
      "-o",
      "obj/Matrix.o",
      "-I",
      "headers",
      "-I",
      "dependencies/mathgl-8.0.3/include"
    ],
    "directory": "/home/yt/Documents/Bachelor Thesis/NN_with_time_signature_feature_map",
    "output": "obj/Matrix.o"
  },
  {
    "file": "src/MemArena.c",
    "arguments": [
      "gcc",
      "-g",
      "-Wall",
      "-std=c11",
      "-fsanitize=address",
      "-c",
      "src/MemArena.c",
      "-o",
      "obj/MemArena.o",
      "-I",
      "headers",
      "-I",
      "dependencies/mathgl-8.0.3/include"
    ],
    "directory": "/home/yt/Documents/Bachelor Thesis/NN_with_time_signature_feature_map",
    "output": "obj/MemArena.o"
  },
  {
    "file": "src/Random.c",
    "arguments": [
      "gcc",
      "-g",
      "-Wall",
      "-std=c11",
      "-fsanitize=address",
      "-c",
      "src/Random.c",
      "-o",
      "obj/Random.o",
      "-I",
      "headers",
      "-I",
      "dependencies/mathgl-8.0.3/include"
    ],
    "directory": "/home/yt/Documents/Bachelor Thesis/NN_with_time_signature_feature_map",
    "output": "obj/Random.o"
  },
  {
    "file": "src/ReactionParser.c",
    "arguments": [
      "gcc",
      "-g",
      "-Wall",
      "-std=c11",
      "-fsanitize=address",
      "-c",
      "src/ReactionParser.c",
      "-o",
      "obj/ReactionParser.o",
      "-I",
      "headers",
      "-I",
      "dependencies/mathgl-8.0.3/include"
    ],
    "directory": "/home/yt/Documents/Bachelor Thesis/NN_with_time_signature_feature_map",
    "output": "obj/ReactionParser.o"
  },
  {
    "file": "src/SRN.c",
    "arguments": [
      "gcc",
      "-g",
      "-Wall",
      "-std=c11",
      "-fsanitize=address",
      "-c",
      "src/SRN.c",
      "-o",
      "obj/SRN.o",
      "-I",
      "headers",
      "-I",
      "dependencies/mathgl-8.0.3/include"
    ],
    "directory": "/home/yt/Documents/Bachelor Thesis/NN_with_time_signature_feature_map",
    "output": "obj/SRN.o"
  },
  {
    "file": "src/TrajectorySim.c",
    "arguments": [
      "gcc",
      "-g",
      "-Wall",
      "-std=c11",
      "-fsanitize=address",
      "-c",
      "src/TrajectorySim.c",
      "-o",
      "obj/TrajectorySim.o",
      "-I",
      "headers",
      "-I",
      "dependencies/mathgl-8.0.3/include"
    ],
    "directory": "/home/yt/Documents/Bachelor Thesis/NN_with_time_signature_feature_map",
    "output": "obj/TrajectorySim.o"
  }
]